ibm_pathfinder_sdk/__init__.py
ibm_pathfinder_sdk/eventpublisher.py
ibm_pathfinder_sdk/pathfinderconfig.py
ibm_pathfinder_sdk/pfmodelclasses.py
ibm_pathfinder_sdk-0.1.8.dist-info/licenses/LICENSE
ibm_pathfinder_sdk-0.1.8.dist-info/METADATA
ibm_pathfinder_sdk-0.1.8.dist-info/WHEEL
ibm_pathfinder_sdk-0.1.8.dist-info/top_level.txt
ibm_pathfinder_sdk-0.1.8.dist-info/RECORD
