Metadata-Version: 2.4
Name: ibm_pathfinder_sdk
Version: 0.1.8
Summary: Parthfinder connector lib package
Author-email: IBM <wci01@zurich.ibm.com>
Project-URL: Homepage, https://github.com/IBM/pathfinder-python-sdk
Project-URL: Bug Tracker, https://github.com/IBM/pathfinder-python-sdk/issues
Classifier: Programming Language :: Python :: 3
Classifier: Programming Language :: Python :: 3.9
Classifier: Programming Language :: Python :: 3.10
Classifier: Programming Language :: Python :: 3.11
Classifier: Operating System :: OS Independent
Classifier: License :: OSI Approved :: Apache Software License
Classifier: Topic :: Software Development :: Libraries :: Python Modules
Classifier: Topic :: Software Development :: Libraries :: Application Frameworks
Requires-Python: >=3.9
License-File: LICENSE
Requires-Dist: requests
Requires-Dist: boto3
Requires-Dist: pyyaml
Requires-Dist: kafka-python
Dynamic: license-file
